AUTHORS.md
CHANGELOG.md
CONTRIBUTING.md
LICENSE
README.md
psi_score/__init__.py
psi_score/linalg/__init__.py
psi_score/linalg/psi_solvers.py
psi_score/linalg/push.py
psi_score/psi_score.py
psi_score/utils.py
psi_score-1.0.0.dist-info/LICENSE
psi_score-1.0.0.dist-info/METADATA
psi_score-1.0.0.dist-info/WHEEL
psi_score-1.0.0.dist-info/RECORD
