Metadata-Version: 2.1
Name: psi-score
Version: 1.0.0
Summary: Metric of user influence in Online Social Networks
Home-page: https://github.com/NouamaneA/psi-score
License: MIT
Keywords: graph algorithms,network science,markov chain,social networks,pagerank
Author: Nouamane Arhachoui
Author-email: nouamane.arhachoui@lip6.fr
Requires-Python: >=3.9,<3.11
Classifier: License :: OSI Approved :: MIT License
Classifier: Programming Language :: Python :: 3
Classifier: Programming Language :: Python :: 3.9
Classifier: Programming Language :: Python :: 3.10
Requires-Dist: numpy (>=1.23.1,<2.0.0)
Requires-Dist: progressbar2 (>=4.0.0,<5.0.0)
Requires-Dist: scipy (>=1.8.1,<2.0.0)
Project-URL: Repository, https://github.com/NouamaneA/psi-score
